[
    {
        "id": 1231,
        "fullname": "John Smith ",
        "date applied": "05/01/2022",
        "status": true
    },
    {
        "id": 1002,
        "fullname": "Emily Johnson ",
        "date applied": "12/03/2022",
        "status": true
    },
    {
        "id": 1003,
        "fullname": "Michael Williams ",
        "date applied": "20/06/2022",
        "status": true
    },
    {
        "id": 1004,
        "fullname": "Jessica Brown ",
        "date applied": "02/09/2022",
        "status": true
    },
    {
        "id": 1005,
        "fullname": "David Jones",
        "date applied": "18/11/2022",
        "status": true
    },
    {
        "id": 1006,
        "fullname": "Sarah Davis ",
        "date applied": "10/02/2022",
        "status": true
    },
    {
        "id": 1007,
        "fullname": "Robert Miller ",
        "date applied": "25/04/2022",
        "status": true
    },
    {
        "id": 1008,
        "fullname": "Jennifer Wilson ",
        "date applied": "07/07/2022",
        "status": true
    },
    {
        "id": 1009,
        "fullname": "William Taylor ",
        "date applied": "15/10  /2022",
        "status": true
    },
    {
        "id": 1010,
        "fullname": "Elizabeth Anderson  ",
        "date applied": "30/12/2022",
        "status": true
    },
    {
        "id": 1011,
        "fullname": "Christopher Clark ",
        "date applied": "08/03/2022",
        "status": false
      },
      {
        "id": 1012,
        "fullname": "Amanda Rodriguez ",
        "date applied": "05/01/2022",
        "status": false
      },
      {
        "id": 1013,
        "fullname": "Matthew Martinez ",
        "date applied": "19/06/2022",
        "status": false
      },
      {
        "id": 1014,
        "fullname": "Laura Lewis ",
        "date applied": "27/09/2022",
        "status": false
      },
      {
        "id": 1015,
        "fullname": "Daniel Lee ",
        "date applied": "04/12/2022",
        "status": false
      },
      {
        "id": 1016,
        "fullname": "Jessica Hernandez  ",
        "date applied": "16/01/2022",
        "status": false
      },
      {
        "id": 1017,
        "fullname": "Brian Gonzalez ",
        "date applied": "23/04/2022",
        "status": false
      },
      {
        "id": 1018,
        "fullname": "Sophia White ",
        "date applied": "07/07/2022",
        "status": false
      },
      {
        "id": 1019,
        "fullname": "James Thompson  ",
        "date applied": "14/10/2022",
        "status": false
      },
      {
        "id": 1020,
        "fullname": "Ashley Hall ",
        "date applied": "29/12/2022",
        "status": false
      },
      {
        "id": 1021,
        "fullname": "Joshua Patel ",
        "date applied": "03/03/2022",
        "priority": false
      },
      {
        "id": 1022,
        "fullname": "Kimberly Mitchell",
        "date applied": "15/05/2022",
        "priority": false
      },
      {
        "id": 1023,
        "fullname": "Joseph Carter ",
        "date applied": "26/08/2022",
        "priority": false
      },
      {
        "id": 1024,
        "fullname": "Mary Adams ",
        "date applied": "09/11/2022",
        "priority": false
      },
      {
        "id": 1025,
        "fullname": "Nicholas Nelson ",
        "date applied": "22/01/2022",
        "priority": false
      },
      {
        "id": 1026,
        "fullname": "Megan Turner  ",
        "date applied": "04/04/2022",
        "priority": false
      },
      {
        "id": 1027,
        "fullname": "Benjamin Scott ",
        "date applied": "10/07/2022",
        "priority": false
      },
      {
        "id": 1028,
        "fullname": "Olivia Phillips ",
        "date applied": "21 /09/2022",
        "priority": false
      },
      {
        "id": 1029,
        "fullname": "Ethan Wilson   ",
        "date applied": "04/12/2022",
        "priority": false
      },
      {
        "id": 1030,
        "fullname": "Ava Martin  ",
        "date applied": "08/02/2022",   
        "priority": false
      }
]
    
   